ebay_pictures_tool/__init__.py
ebay_pictures_tool/com.shiny.folder-listener.plist
ebay_pictures_tool/main.py
ebay_pictures_tool/secret.json.sample
ebay_pictures_tool-0.0.95.dist-info/METADATA
ebay_pictures_tool-0.0.95.dist-info/WHEEL
ebay_pictures_tool-0.0.95.dist-info/entry_points.txt
ebay_pictures_tool-0.0.95.dist-info/RECORD
