Metadata-Version: 2.1
Name: ebay_pictures_tool
Version: 0.0.95
Summary: An efficient tool for processing ebay images.
Author: Chris Busillo
Author-email: cbusillo@gmail.com
Requires-Python: >=3.11,<3.12
Classifier: Programming Language :: Python :: 3
Classifier: Programming Language :: Python :: 3.11
Requires-Dist: colour (>=0.1.5,<0.2.0)
Requires-Dist: llvmlite (>=0.40.1,<0.41.0)
Requires-Dist: numba (>=0.57.1,<0.58.0)
Requires-Dist: opencv-python (>=4.8.0.76,<5.0.0.0)
Requires-Dist: pyzbar (>=0.1.9,<0.2.0)
Requires-Dist: rembg (>=2.0.50,<3.0.0)
